polars_genson/__init__.py
polars_genson/__init__.pyi
polars_genson/_polars_genson.pypy311-pp73-x86_64-linux-gnu.so
polars_genson/dtypes.py
polars_genson/polars.pyi
polars_genson/py.typed
polars_genson/utils.py
polars_genson-0.7.4.dist-info/METADATA
polars_genson-0.7.4.dist-info/WHEEL
polars_genson-0.7.4.dist-info/RECORD
