Metadata-Version: 2.4
Name: polars-genson
Version: 0.7.4
Classifier: Development Status :: 4 - Beta
Classifier: Intended Audience :: Developers
Classifier: License :: OSI Approved :: MIT License
Classifier: Natural Language :: English
Classifier: Operating System :: OS Independent
Classifier: Programming Language :: Python :: 3
Classifier: Programming Language :: Python :: 3.10
Classifier: Programming Language :: Python :: 3.11
Classifier: Programming Language :: Python :: 3.12
Classifier: Programming Language :: Python :: 3.13
Classifier: Programming Language :: Python :: 3.9
Classifier: Programming Language :: Python :: Implementation :: CPython
Classifier: Programming Language :: Python
Requires-Dist: orjson>=3.11.2
Requires-Dist: pdm-bump>=0.9.10 ; extra == 'dev'
Requires-Dist: pdm>=2.22.3 ; extra == 'dev'
Requires-Dist: pre-commit>=4.1.0 ; extra == 'dev'
Requires-Dist: pytest>=8.3.4 ; extra == 'dev'
Requires-Dist: polars>=1.32.0,!=1.32.3,!=1.33.0,!=1.33.1 ; extra == 'polars'
Requires-Dist: polars-lts-cpu>=1.32.0,!=1.32.3,!=1.33.0,!=1.33.1 ; extra == 'polars-lts-cpu'
Provides-Extra: dev
Provides-Extra: polars
Provides-Extra: polars-lts-cpu
Summary: A Polars plugin for JSON schema inference using genson-rs.
Author-email: Louis Maddox <louismmx@gmail.com>
Requires-Python: >=3.9
Project-URL: Homepage, https://github.com/lmmx/polars-genson
Project-URL: Repository, https://github.com/lmmx/polars-genson.git
